[
    {
        "name": "Discovering Computer Science",
        "id": "100",
        "credit_hours": "3",
        "description": "Fundamentals of computing; history of computation; computer organization; program design, testing and debugging; web design; computer animation; software tools; societal and legal issues in computing. ",
        "topics": ["Python", "Projects","Debugging"],
        "difficulty": 1,
        "favorite": true,
        "prereqs": ["101", "102", "103"],
        "typical_yr": "freshmen",
        "sections": ["lecture-discussion", "lab"],
        "image-url": "/../../assets/flowcharts/engr100.png",
        "course-type": "engineering-requirement"
    },
    {
        "name": "Introduction to Computing and Programming",
        "id": "107",
        "credit_hours": "4",
        "description": "Access and use of computing resources. Programming and program design. Problem solving. Data types, control structures, modularity, information hiding. ",
        "topics": ["Programming Basics", "Program Design"],
        "difficulty": 1,
        "favorite": true,
        "prereqs": [],
        "typical_yr": "freshmen",
        "sections": ["lecture", "lab"],
        "image-url": "/../../assets/flowcharts/general.png",
        "course-type": "technical-elective"
    },
    {
        "name": "Programming for Engineers with MatLab",
        "id": "109",
        "credit_hours": "3",
        "description": "Develop an understanding of program design using data types, operators, control structures, functions, file I/O, arrays and structures.  Demonstrate the understanding through computer projects with engineering applications. ",
        "topics": ["Program Design", "Data types", "Operators"],
        "difficulty": 1,
        "favorite": false,
        "prereqs": [],
        "typicalYear": "freshmen",
        "sections": ["lecture-discussion", "lab-discussion"],
        "image-url": "/../../assets/flowcharts/general.png",
        "course-type": "engineering-requirement"
    },
    {
        "name": "Program Design I",
        "id": "111",
        "credit_hours": "3",
        "description": "Introduction to programming: control structures; variables and data types; problem decomposition and procedural programming; input and output; aggregate data structures including arrays; programming exercises. ",
        "topics": ["Python","Problem Decomposition", "Programming Basics", "C", "C++"],
        "difficulty": 1,
        "favorite": true,
        "prereqs": [],
        "typicalYear": "freshmen",
        "sections": ["lecture-discussion", "lab"],
        "image-url": "/../../assets/flowcharts/cs111.png",
        "course-type": "engineering-requirement"
    },
    {
        "name": "Program Design I in the Context of Biological Problems",
        "id": "112",
        "credit_hours": "3",
        "description": "Introduction to programming using Biology as the context for programming in a high-level language; control structures, variables, simple and aggregate data types; problem-solving techniques; biology topics include central dogma and genetics. ",
        "topics": ["Programming Basics", "Control Structures", "Variables"],
        "difficulty": 1,
        "favorite": true,
        "prereqs": [],
        "typicalYear": "freshmen",
        "sections": ["lecture-discussion", "lab"],
        "image-url": "/../../assets/flowcharts/cs111.png",
        "course-type": "engineering-requirement"
    },
    {
        "name": "Program Design I in the Context of Law and Public Policy",
        "id": "113",
        "credit_hours": "3",
        "description": "Introduction to programming using law and public policy as the context for programming; control structures, variables, simple and aggregate data types; problem-solving techniques; legal topics: security, privacy, encryption, and predictive policing. ",
        "topics": ["Programming Basics","Security", "Privacy"],
        "difficulty": 1,
        "favorite": true,
        "prereqs": [],
        "typicalYear": "freshmen",
        "sections": ["lecture-discussion", "lab"],
        "image-url": "/../../assets/flowcharts/cs111.png",
        "course-type": "engineering-requirement"
    },
    {
        "name": "Program Design II",
        "id": "141",
        "credit_hours": "3",
        "description": "Data abstraction and modular design; recursion; lists and stacks; dynamic memory allocation; file manipulation; programming exercises. ",
        "topics": ["C++", "Classes", "Pointers", "Programming Logic"],
        "difficulty": 2,
        "favorite": true,
        "prereqs": ["111"],
        "typicalYear": "freshmen",
        "sections": ["lecture-discussion", "lab-discussion"],
        "image-url": "/../../assets/flowcharts/cs141.png",
        "course-type": "engineering-requirement"
    },
    {
        "name": "Mathematical Foundations of Computing",
        "id": "151",
        "credit_hours": "3",
        "description": "Discrete mathematics concepts fundamental to computing:  propositional logic, predicates and quantifiers; proofs; sets; recursive definitions and  induction; functions, relations and graphs; combinatorics and discrete probability; applications. ",
        "topics": ["Discrete Mathematics", "Predicate Logic", "Proofs", "Induction"],
        "difficulty": 3,
        "favorite": true,
        "prereqs": ["111"],
        "typicalYear": "freshmen",
        "sections": ["lecture", "discussion"],
        "image-url": "/../../assets/flowcharts/cs151.png",
        "course-type": "engineering-requirement"
    },
    {
        "name": "Special Topics in Computer Science",
        "id": "194",
        "credit_hours": "1-3",
        "description": "Multidisciplinary computer science topics at first-year level that vary from term to term depending on current student and instructor interests.",
        "topics": ["Multidisciplinary"],
        "difficulty": 2,
        "favorite": true,
        "prereqs": [],
        "typicalYear": "freshmen",
        "sections": ["VARIES"],
        "image-url": "/../../assets/flowcharts/151.png",
        "course-type": "engineering-requirement"
    },
    {
        "name": "Programming Practicum",
        "id": "211",
        "credit_hours": "3",
        "description": "Software development tools and practices; debugging and testing; advanced language features; standard libraries; code management. ",
        "topics": ["C", "C++", "Program Design", "Memory Allocation"],
        "difficulty": 4,
        "favorite": true,
        "prereqs": ["141"],
        "typicalYear": "sophomore",
        "sections": ["lecture-discussion", "lab-discussion"],
        "image-url": "/../../assets/flowcharts/cs211.png",
        "course-type": "engineering-requirement"
    },
    {
        "name": "Data Structures",
        "id": "251",
        "credit_hours": "4",
        "description": "Design, usage and analysis of data structures:  review of lists, stacks and  queues; hash tables, priority queues, search trees, introduction  to graphs;  searching and sorting; runtime analysis; programming projects and lab exercises. ",
        "topics": ["C++", "Data Structures", "Algorithms"],
        "difficulty": 4,
        "favorite": true,
        "prereqs": ["141", "211"],
        "typicalYear": "sophomore",
        "sections": ["lecture-discussion", "lab"],
        "image-url": "/../../assets/flowcharts/cs251.png",
        "course-type": "engineering-requirement"
    },
    {
        "name": "Machine Organization",
        "id": "261",
        "credit_hours": "4",
        "description": "Data representation and computer arithmetic; machine language; addressing; memory hierarchy; subroutines; data structures; processor architecture: hardware components, pipelining. ",
        "topics": ["Assembly x86-64", "Memory", "Machine Language"],
        "difficulty": 5,
        "favorite": true,
        "prereqs": ["141", "211"],
        "typicalYear": "sophomore",
        "sections": ["lecture-discussion", "lab"],
        "image-url": "/../../assets/flowcharts/cs261.png",
        "course-type": "engineering-requirement"
    },
    {
        "name": "Technical and Professional Communication in Computer Science",
        "id": "277",
        "credit_hours": "3",
        "description": "Communication skills for computing students and professionals in various contexts: technical writing, portfolios, job interviews, demos, sales, with speech organization, visuals, and delivery. Attendance, participation, and presentations required. ",
        "topics": ["Technical Communication", "Communication Skills", "Professional Prep"],
        "difficulty": 1,
        "favorite": true,
        "prereqs": ["141"],
        "typicalYear": "sophomore",
        "sections": ["lecture-discussion", "discussion"],
        "image-url": "/../../assets/flowcharts/cs277.png",
        "course-type": "engineering-requirement"
    },
    {
        "name": "Special Topics in Computer Science",
        "id": "294",
        "credit_hours": "1-3",
        "description": "Multidisciplinary computer science topics at sophomore level that vary from term to term depending on current student and instructor interests. ",
        "topics": ["Multidisciplinary"],
        "difficulty": 2,
        "favorite": true,
        "prereqs": [],
        "typicalYear": "sophomore",
        "sections": ["VARIES"],
        "image-url": "/../../assets/flowcharts/general.png",
        "course-type": "engineering-requirement"
    },
    {
        "name": "Languages and Automata",
        "id": "301",
        "credit_hours": "3",
        "description": "Regular sets and finite automata. Context-free languages and push-down automata. Parsing. Computability theory including Turing machines and decidability. ",
        "topics": ["Theory", "Finite Automata", "Pumping Lemma", "Turing Machine"],
        "difficulty": 2.5,
        "favorite": true,
        "prereqs": ["151","251"],
        "typicalYear": "junior",
        "sections": ["discussion/recitation", "lecture"],
        "image-url": "/../../assets/flowcharts/general.png",
        "course-type": "engineering-requirement"
    },
    {
        "name": "Programming Language Design and Implementation",
        "id": "341",
        "credit_hours": "3",
        "description": "Programming language paradigms, design and implementation: syntax and semantics; parsing; runtime systems; control;  data types; subroutines and exceptions; data and procedural abstraction; functional programming. ",
        "topics": ["Python", "SQL", "F#", "C", "Program Design"],
        "difficulty": 4,
        "favorite": true,
        "prereqs": ["211", "251"],
        "typicalYear": "junior",
        "sections": ["lecture"],
        "image-url": "/../../assets/flowcharts/cs341.png",
        "course-type": "engineering-requirement"
    },
    {
        "name": "Software Design",
        "id": "342",
        "credit_hours": "3",
        "description": "Software design principles and practices: Object-oriented design; design patterns; software reuse; testing;  event driven programming and concurrency; graphical user interface design and development; Team development. ",
        "topics": ["Program Design", "Object Oriented", "Software Engineering"],
        "difficulty": 4,
        "favorite": true,
        "prereqs": ["211", "251"],
        "typicalYear": "junior",
        "sections": ["lecture"],
        "image-url": "/../../assets/flowcharts/cs342.png",
        "course-type": "engineering-requirement"
    },
    {
        "name": "Advanced Data Structure Practicum",
        "id": "351",
        "credit_hours": "3",
        "description": "Design and implementation details of advanced data structure and non-trivial algorithms with an emphasis on amortized analysis. ",
        "topics": ["Data Structures", "Program Design", "Algorithms"],
        "difficulty": 3.5,
        "favorite": true,
        "prereqs": ["251"],
        "typicalYear": "junior",
        "sections": ["lecture"],
        "image-url": "/../../assets/flowcharts/general.png",
        "course-type": "engineering-requirement"
    },
    {
        "name": "Systems Programming",
        "id": "361",
        "credit_hours": "4",
        "description": "Study of computer systems emphasizing impact on application level programming. Virtual memory and memory management; code optimization; system-level I/O; concurrency:  processes, threads, synchronization; introduction to network programming. ",
        "topics": ["Systems Programming", "C", "Networking"],
        "difficulty": 5,
        "favorite": true,
        "prereqs": ["211", "251", "261"],
        "typicalYear": "junior",
        "sections": ["lecture-discussion", "lab"],
        "image-url": "/../../assets/flowcharts/cs361.png",
        "course-type": "engineering-requirement"
    },
    {
        "name": "Computer Design",
        "id": "362",
        "credit_hours": "4",
        "description": "Computer hardware building blocks.  logic gates; combinational circuits; arithmetic circuits; flip flops and sequential circuits; registers and memory; CPU design; I/O design. ",
        "topics": ["Hardware", "Logic Gates", "Memory", "Circuits"],
        "difficulty": 5,
        "favorite": true,
        "prereqs": ["211", "261"],
        "typicalYear": "junior",
        "sections": ["lecture-discussion", "lab"],
        "image-url": "/../../assets/flowcharts/cs362.png",
        "course-type": "engineering-requirement"
    },
    {
        "name": "Ethical Issues in Computing",
        "id": "377",
        "credit_hours": "3",
        "description": "Communication skills for computing professionals: presentation organization, visual aides, delivery techniques, argument support. Ethical and societal issues in computing: privacy, intellectual property and ownership, crime. ",
        "topics": ["Ethics", "Communication Skills", "Societial Issues"],
        "difficulty": 1,
        "favorite": true,
        "prereqs": ["251"],
        "typicalYear": "junior",
        "sections": ["lecture-discussion", "discussion"],
        "image-url": "/../../assets/flowcharts/cs377.png",
        "course-type": "engineering-requirement"
    },
    {
        "name": "Framework-based Software Development for Hand-held Devices",
        "id": "378",
        "credit_hours": "3",
        "description": "Multi-platform app development using software frameworks; the integration of framework-generated code with native code of mobile operating systems; numerous programming assignments in multiple programming languages. ",
        "topics": ["Software Engineering", "Software Frameworks", "Programming Logic"],
        "difficulty": 3,
        "favorite": true,
        "prereqs": ["342"],
        "typicalYear": "junior",
        "sections": ["lecture"],
        "image-url": "/../../assets/flowcharts/general.png",
        "course-type": "engineering-requirement"
    },
    {
        "name": "Computer Science Practicum",
        "id": "391",
        "credit_hours": "1",
        "description": "Provides students with the opportunity to apply the skills and knowledge gained in previous engineering courses within a professional, working environment. ",
        "topics": ["Programming Logic", "Multidisciplinary"],
        "difficulty": 3,
        "favorite": true,
        "prereqs": [],
        "typicalYear": "junior",
        "sections": ["lab-discussion"],
        "image-url": "/../../assets/flowcharts/general.png",
        "course-type": "engineering-requirement"
    },
    {
        "name": "Special Topics in Computer Science",
        "id": "394",
        "credit_hours": "1-3",
        "description": "Multidisciplinary computer science topics at junior-senior level that vary from term to term depending on current student and instructor interests. ",
        "topics": ["Multidisciplinary"],
        "difficulty": 3,
        "favorite": true,
        "prereqs": [],
        "typicalYear": "junior",
        "sections": ["VARIES"],
        "image-url": "/../../assets/flowcharts/general.png",
        "course-type": "technical-elective"
    },
    {
        "name": "Undergraduate Design/Research",
        "id": "398",
        "credit_hours": "1-3",
        "description": "Design and/or research experience for undergraduate Computer Science majors under close supervision of a CS faculty member. ",
        "topics": ["Design", "Research", "Multidisciplinary"],
        "difficulty": 2,
        "favorite": true,
        "prereqs": [],
        "typicalYear": "junior",
        "sections": ["lab-discussion"],
        "image-url": "/../../assets/flowcharts/general.png",
        "course-type": "technical-elective"
    },
    {
        "name": "Computer Algorithms I",
        "id": "401",
        "credit_hours": "3",
        "description": "Design and analysis of computer algorithms. Divide-and-conquer, dynamic programming, greedy method, backtracking. Algorithms for sorting, searching, graph computations, pattern matching, NP-complete problems. ",
        "topics": ["Theory", "Algorithms", "Dynamic Programming"],
        "difficulty": 3,
        "favorite": true,
        "prereqs": ["251"],
        "typicalYear": "senior",
        "sections": ["lecture"],
        "image-url": "/../../assets/flowcharts/cs401.png",
        "course-type": "engineering-requirement"
    },
    {
        "name": "Algorithms in Practice",
        "id": "402",
        "credit_hours": "3",
        "description": "Design, implementation and presentation of algorithms and data structures emphasizing dynamic programming and both exact and heuristic approaches to NP-hard problems; problem solving sessions, programming projects and presentations. ",
        "topics": ["Design", "Applications", "Algorithms", "Dynamic Programming"],
        "difficulty": 3,
        "favorite": true,
        "prereqs": ["401"],
        "typicalYear": "senior",
        "sections": ["lecture-discussion"],
        "image-url": "/../../assets/flowcharts/general.png",
        "course-type": "technical-elective"
    },
    {
        "name": "Economics and Computation",
        "id": "407",
        "credit_hours": "3",
        "description": "Techniques for analysis of markets, making decisions with other strategic agents, and understanding how algorithms affect the incentives of market participants. These include game theory, mechanism design, auction theory, and social choice theory. ",
        "topics": ["Economics", "Analysis", "Market", "Theory"],
        "difficulty": 3,
        "favorite": true,
        "prereqs": ["251"],
        "typicalYear": "senior",
        "sections": ["lecture-discussion"],
        "image-url": "/../../assets/flowcharts/general.png",
        "course-type": "technical-elective"
    },
    {
        "name": "Artificial Intelligence I",
        "id": "411",
        "credit_hours": "3",
        "description": "Problem representation; rule-based problem-solving methods; heuristic search techniques. Application to expert systems, theorem proving, language understanding. Individual projects. ",
        "topics": ["Python", "Algorithms", "Markov Models", "Artificial Intelligience"],
        "difficulty": 3,
        "favorite": true,
        "prereqs": ["251"],
        "typicalYear": "senior",
        "sections": ["lecture-discussion"],
        "image-url": "/../../assets/flowcharts/cs411.png",
        "course-type": "technical-elective"
    },
    {
        "name": "Introduction to Machine Learning",
        "id": "412",
        "credit_hours": "3",
        "description": "Mechanism, implementation, and application of systems that improve automatically based on past experience, including classification, density estimation, clustering, and online learning tasks and solutions. ",
        "topics": ["Machine Learning", "Applications", "Systems"],
        "difficulty": 3,
        "favorite": true,
        "prereqs": ["251"],
        "typicalYear": "senior",
        "sections": ["lecture-discussion"],
        "image-url": "/../../assets/flowcharts/cs412.png",
        "course-type": "technical-elective"
    },
    {
        "name": "Computer Vision I",
        "id": "415",
        "credit_hours": "3",
        "description": "Computer vision system design. Segmentation and representation of regions and boundaries; image filtering; object recognition; advanced topics (examples: texture, stereo, color); applications. Programming assignments. ",
        "topics": ["Image Filtering", "Object Recognition", "Applications"],
        "difficulty": 3,
        "favorite": true,
        "prereqs": ["202"],
        "typicalYear": "senior",
        "sections": ["lecture-discussion"],
        "image-url": "/../../assets/flowcharts/general.png",
        "course-type": "technical-elective"
    },
    {
        "name": "Introduction to Data Science",
        "id": "418",
        "credit_hours": "3",
        "description": "Provides an in-depth overview of data science in engineering. Topics include modeling, storage, manipulation, integration, classification, analysis, visualization, information extraction, and big data in the engineering domain. ",
        "topics": ["Python", "Data Science", "Analysis"],
        "difficulty": 2.5,
        "favorite": true,
        "prereqs": ["251"],
        "typicalYear": "senior",
        "sections": ["lecture-discussion"],
        "image-url": "/../../assets/flowcharts/cs418.png",
        "course-type": "technical-elective"
    },
    {
        "name": "Natural Language Processing",
        "id": "421",
        "credit_hours": "3",
        "description": "Design of natural language processing systems; part-of speech tagging, statistical and symbolic parsers; semantic interpretation; discourse and dialogue processing; natural language generation; applications. ",
        "topics": ["Natural Language", "Applications", "Processing"],
        "difficulty": 3,
        "favorite": true,
        "prereqs": ["301"],
        "typicalYear": "senior",
        "sections": ["lecture-discussion"],
        "image-url": "/../../assets/flowcharts/cs421.png",
        "course-type": "technical-elective"
    },
    {
        "name": "User Interface Design and Programming",
        "id": "422",
        "credit_hours": "3",
        "description": "User interface design, implementation, and evaluation: user-centered design methodologies, windowing systems, I/O devices and techniques, event-loop programming, user studies. Programming projects. ",
        "topics": ["User Interface", "Design", "I/O Devices"],
        "difficulty": 2,
        "favorite": true,
        "prereqs": ["342"],
        "typicalYear": "senior",
        "sections": ["lecture-discussion"],
        "image-url": "/../../assets/flowcharts/cs422.png",
        "course-type": "technical-elective"
    },
    {
        "name": "Natural User Interactions",
        "id": "423",
        "credit_hours": "3",
        "description": "Introduces students to the field of natural user interactions, including topics such as design principles, hardware-to-software development pipeline (including various existing platforms, toolkits and APIs), as well as effective evaluation techniques. ",
        "topics": ["Design", "Hardware", "Software"],
        "difficulty": 2,
        "favorite": true,
        "prereqs": ["342"],
        "typicalYear": "senior",
        "sections": ["lecture-discussion"],
        "image-url": "/../../assets/flowcharts/general.png",
        "course-type": "technical-elective"
    },
    {
        "name": "Visualization and Visual Analytics",
        "id": "424",
        "credit_hours": "3",
        "description": "Geospatial visualization, scientific visualization, medical visualization, information visualization, and social network visualization, interaction, data analysis, human factors, dynamic data, privacy, uncertainty, data transforms. ",
        "topics": ["Visualization", "Analysis", "Dynamic Data"],
        "difficulty": 3,
        "favorite": true,
        "prereqs": ["251"
        ],
        "typicalYear": "senior",
        "sections": ["lecture-discussion"],
        "image-url": "/../../assets/flowcharts/general.png",
        "course-type": "technical-elective"
    },
    {
        "name": "Computer Graphics I",
        "id": "425",
        "credit_hours": "0-4",
        "description": "Principles of interactive computer graphics. Raster and vector display, techniques and hardware considerations. Introduction to two-dimensional and three dimensional rendering. ",
        "topics": ["Graphics Rendering", "Vector Display", "Hardware"],
        "difficulty": 3,
        "favorite": true,
        "prereqs": ["251"],
        "typicalYear": "senior",
        "sections": ["lecture-discussion", "lab-discussion"],
        "image-url": "/../../assets/flowcharts/cs425.png",
        "course-type": "technical-elective"
    },
    {
        "name": "Video Game Design and Development",
        "id": "426",
        "credit_hours": "3",
        "description": "Theory and practice of video game design and programming. Students will form interdisciplinary teams, to design, build and demonstrate video games or related interactive simulation environments. ",
        "topics": ["Video Game Design", "Development"],
        "difficulty": 2.5,
        "favorite": true,
        "prereqs": ["251"],
        "typicalYear": "senior",
        "sections": ["lecture-discussion"],
        "image-url": "/../../assets/flowcharts/cs426.png",
        "course-type": "technical-elective"
    },
    {
        "name": "Creative Coding",
        "id": "427",
        "credit_hours": "3",
        "description": "Creative Coding investigates how contemporary computational techniques can inspire novel forms of art making, providing students with the skills to make use of technology for expressive purposes. ",
        "topics": ["Creativity", "Contemporary Computation"],
        "difficulty": 2.5,
        "favorite": true,
        "prereqs": ["251"],
        "typicalYear": "senior",
        "sections": ["lecture-discussion"],
        "image-url": "/../../assets/flowcharts/general.png",
        "course-type": "technical-elective"
    },
    {
        "name": "Virtual, Augmented, and Mixed Reality",
        "id": "428",
        "credit_hours": "3",
        "description": "Virtual reality, augmented reality, and mixed reality environments, display devices, input devices, tracking, navigation, interaction, collaboration, generating visuals and sounds, software tools, applications, evaluation, safety. ",
        "topics": ["Virtual Reality", "Visualization", "Applications"] ,
        "difficulty": 3,
        "favorite": true,
        "prereqs": ["342"],
        "typicalYear": "senior",
        "sections": ["lecture-discussion"],
        "image-url": "/../../assets/flowcharts/general.png",
        "course-type": "engineering-requirement"
    },
    {
        "name": "Software Engineering I",
        "id": "440",
        "credit_hours": "3",
        "description": "Software life-cycle model, requirement specification techniques, large-scale software design techniques and tools, implementation issues, testing and debugging techniques, software maintenance. ",
        "topics": ["Software Frameworks", "Program Design", "Software Engineering"],
        "difficulty": 5,
        "favorite": true,
        "prereqs": ["342"],
        "typicalYear": "senior",
        "sections": ["lecture-discussion"],
        "image-url": "/../../assets/flowcharts/cs440.png",
        "course-type": "engineering-requirement"
    },
    {
        "name": "Engineering Distributed Objects For Cloud Computing",
        "id": "441",
        "credit_hours": "3",
        "description": "Provides a broad but solid overview of engineering distributed object for cloud computing. Students will learn the theory and principles of engineering distributed objects for cloud environments. Programming assignments required. ",
        "topics": ["Object Oriented", "Cloud Computation"],
        "difficulty": 5,
        "favorite": true,
        "prereqs": ["341", "342", "361"],
        "typicalYear": "senior",
        "sections": ["lecture-discussion"],
        "image-url": "/../../assets/flowcharts/general.png",
        "course-type": "engineering-requirement"
    },
    {
        "name": "Software Engineering II",
        "id": "442",
        "credit_hours": "3",
        "description": "Advanced concepts in software development: requirements engineering, cost estimation, risk analysis, extreme programming, regression test case selection, and design patterns.  Software lab assignments required.  ",
        "topics": ["Software Engineering", "Analysis", "Design"],
        "difficulty": 5,
        "favorite": true,
        "prereqs": ["440"],
        "typicalYear": "senior",
        "sections": ["lecture-discussion"],
        "image-url": "/../../assets/flowcharts/general.png",
        "course-type": "engineering-requirement"
    },
    {
        "name": "Introduction to Networking",
        "id": "450",
        "credit_hours": "3",
        "description": "Network protocols, algorithms, and software issues. Topics include the Open Systems Interconnect model, data link, network and transport layers, TCP/IP, ATM, mobile networks. ",
        "topics": ["Algorithms", "Networking", "TCP/IP"],
        "difficulty": 5,
        "favorite": true,
        "prereqs": ["361"],
        "typicalYear": "senior",
        "sections": ["lecture-discussion"],
        "image-url": "/../../assets/flowcharts/cs450.png",
        "course-type": "engineering-requirement"
    },
    {
        "name": "Introduction to Parallel and Distributed Processing",
        "id": "453",
        "credit_hours": "3",
        "description": "Foundations of parallel and distributed processing; clusters and parallel systems; communication primitives; programming with MPI; scalability; distributed graph algorithms; distributed mutual exclusion, deadlock detection, peer-to-peer systems. ",
        "topics": ["Parallel Processing", "Distributed Processing", "Algorithms"],
        "difficulty": 5,
        "favorite": true,
        "prereqs": ["401"],
        "typicalYear": "senior",
        "sections": ["lecture-discussion"],
        "image-url": "/../../assets/flowcharts/general.png",
        "course-type": "engineering-requirement"
    },
    {
        "name": "Principles of Concurrent Programming",
        "id": "454",
        "credit_hours": "3",
        "description": "Focuses on the foundations and basic principles of concurrent programming, covering high-level notions of concurrent correctness and connecting those abstract concepts to real-world programming constructs and algorithms used in practice. ",
        "topics": ["Concurrent Programming", "Algorithms"],
        "difficulty": 5,
        "favorite": true,
        "prereqs": ["361"],
        "typicalYear": "senior",
        "sections": ["lecture-discussion"],
        "image-url": "/../../assets/flowcharts/general.png",
        "course-type": "engineering-requirement"
    },
    {
        "name": "Introduction to High Performance Computing",
        "id": "455",
        "credit_hours": "3",
        "description": "Explore the foundations of high-performance computing (HPC), the architecture of supercomputers, and the challenges in developing massive heterogeneous systems to address complex real-world problems. ",
        "topics": ["High-Performance Computing", "Supercomputers", "Systems"],
        "difficulty": 5,
        "favorite": true,
        "prereqs": ["361"],
        "typicalYear": "senior",
        "sections": ["lecture-discussion"],
        "image-url": "/../../assets/flowcharts/general.png",
        "course-type": "engineering-requirement"
    },
    {
        "name": "Operating Systems Design and Implementation",
        "id": "461",
        "credit_hours": "3",
        "description": "Kernel design and implementation; process management; effective management of machine resources: resource allocation and scheduling, mutual exclusion, deadlock avoidance, memory management policies, devices and file systems, and client-server systems. ",
        "topics": ["Operating Systems", "Design", "Systems"],
        "difficulty": 5,
        "favorite": true,
        "prereqs": ["361"],
        "typicalYear": "senior",
        "sections": ["lecture-discussion"],
        "image-url": "/../../assets/flowcharts/cs461.png",
        "course-type": "engineering-requirement"
    },
    {
        "name": "Systems Performance and Concurrent Computing",
        "id": "463",
        "credit_hours": "3",
        "description": "Understanding the many systems factors that affect program performance, including program design for concurrent computing, profiling and program optimization. ",
        "topics": ["Systems", "Concurrent Computing", "Program Design"],
        "difficulty": 5,
        "favorite": true,
        "prereqs": ["361"],
        "typicalYear": "senior",
        "sections": ["lecture-discussion"],
        "image-url": "/../../assets/flowcharts/general.png",
        "course-type": "engineering-requirement"
    },
    {
        "name": "Computer Architecture",
        "id": "466",
        "credit_hours": "3",
        "description": "Design principles of computer architecture. Topics include: instruction set architecture, pipelining, instruction-level parallelism, caches, main memory, and thread-level parallelism. ",
        "topics": ["Computer Architecture", "Pipelining", "Cache", "Memory"],
        "difficulty": 5,
        "favorite": true,
        "prereqs": ["261"],
        "typicalYear": "senior",
        "sections": ["lecture-discussion"],
        "image-url": "/../../assets/flowcharts/general.png",
        "course-type": "engineering-requirement"
    },
    {
        "name": "Network Security",
        "id": "468",
        "credit_hours": "3",
        "description": "Introduces basic concepts of security and privacy, and covers the principles and practice of network security. Given the ubiquitousness of network communications, this course explores a range of systems and applications, and the threats they face. ",
        "topics": ["Networking", "Network Security", "Systems"],
        "difficulty": 5,
        "favorite": true,
        "prereqs": ["361"],
        "typicalYear": "senior",
        "sections": ["lecture-discussion"],
        "image-url": "/../../assets/flowcharts/general.png",
        "course-type": "engineering-requirement"
    },
    {
        "name": "Provably Correct Programming",
        "id": "472",
        "credit_hours": "3",
        "description": "Introduction to interactive theorem proving and program logics, with the goal of specifying and proving the correctness of programs. Learn to develop machine-assisted formal mathematical proofs and prove that programs satisfy their specifications. ",
        "topics": ["Theory", "Proofs", "Programming Logic"],
        "difficulty": 5,
        "favorite": true,
        "prereqs": ["341"],
        "typicalYear": "senior",
        "sections": ["lecture-discussion"],
        "image-url": "/../../assets/flowcharts/general.png",
        "course-type": "technical-elective"
    },
    {
        "name": "Compiler Design",
        "id": "473",
        "credit_hours": "3",
        "description": "Language translation: lexical analysis, parsing schemes, symbol table management, syntax and semantic error detection, and code generation. Development of fully-functional compiler. ",
        "topics": ["Machine Language", "Compiler Design", "Syntax"],
        "difficulty": 5,
        "favorite": true,
        "prereqs": ["251", "261", "301"],
        "typicalYear": "senior",
        "sections": ["lecture-discussion"],
        "image-url": "/../../assets/flowcharts/general.png",
        "course-type": "technical-elective"
    },
    {
        "name": "Object-Oriented Languages and Environments",
        "id": "474",
        "credit_hours": "3",
        "description": "Data abstraction, classes and objects, messages and methods, polymorphism and dynamic binding, inheritance. Object-oriented design. Pure and hybrid object-oriented languages. ",
        "topics": ["SQL", "Object Oriented", "DBMS"],
        "difficulty": 5,
        "favorite": true,
        "prereqs": ["342"],
        "typicalYear": "senior",
        "sections": ["lecture-discussion"],
        "image-url": "/../../assets/flowcharts/general.png",
        "course-type": "technical-elective"
    },
    {
        "name": "Object-Oriented Programming",
        "id": "475",
        "credit_hours": "3",
        "description": "OO Paradigm: classes, messages, methods, variables, inheritance, polymorphism; the C++ and Java languages; programming labs required. ",
        "topics": ["Object Oriented", "Polymorphism", "C++", "Java"],
        "difficulty": 5,
        "favorite": true,
        "prereqs": ["202"],
        "typicalYear": "senior",
        "sections": ["lecture-discussion"],
        "image-url": "/../../assets/flowcharts/general.png",
        "course-type": "technical-elective"
    },
    {
        "name": "Programming Language Design",
        "id": "476",
        "credit_hours": "3",
        "description": "Definition, design, and implementation of programming languages. Syntactic and semantic description; variable bindings, control and data structures, parsing, code generation, optimization; exception handling; data abstraction. ",
        "topics": ["Program Design", "Data Structures", "Optimization"],
        "difficulty": 5,
        "favorite": true,
        "prereqs": ["341"],
        "typicalYear": "senior",
        "sections": ["lecture-discussion"],
        "image-url": "/../../assets/flowcharts/general.png",
        "course-type": "technical-elective"
    },
    {
        "name": "Public Policy, Legal, and Ethical Issues in Computing, Privacy, and Security",
        "id": "477",
        "credit_hours": "3",
        "description": "Contemporary topics involving legal, public policy, and/or ethical issues in computing, especially privacy, security, and surveillance. ",
        "topics": ["Public Policy", "Ethics", "Societial Issues", "Security"],
        "difficulty": 5,
        "favorite": true,
        "prereqs": [],
        "typicalYear": "senior",
        "sections": ["lecture-discussion"],
        "image-url": "/../../assets/flowcharts/general.png",
        "course-type": "technical-elective"
    },
    {
        "name": "Software Development for Mobile Platforms",
        "id": "478",
        "credit_hours": "3",
        "description": "Design and implementation of mobile applications; operating systems, object-oriented languages and programming environments for mobile platforms; integration with hardware components; and location-aware applications. Programming assignments required. ",
        "topics": ["Software Engineering", "Mobile Applications", "Operating Systems", "Object Oriented"],
        "difficulty": 3,
        "favorite": true,
        "prereqs": ["342"],
        "typicalYear": "senior",
        "sections": ["lecture-discussion"],
        "image-url": "/../../assets/flowcharts/cs478.png",
        "course-type": "technical-elective"
    },
    {
        "name": "Wearables and Nearables Technology Laboratory",
        "id": "479",
        "credit_hours": "3",
        "description": "Practical experience in design and development of wearable and nearable devices. Acquisition and processing of sensors data. Design and development of user-friendly user interface. ",
        "topics": ["Hardware", "Wearable Tech", "Applications", "User Interface", "Design"],
        "difficulty": 4,
        "favorite": true,
        "prereqs": ["251"],
        "typicalYear": "senior",
        "sections": ["lecture-discussion"],
        "image-url": "/../../assets/flowcharts/general.png",
        "course-type": "technical-elective"
    },
    {
        "name": "Database Systems",
        "id": "480",
        "credit_hours": "3",
        "description": "Database design, logical design, physical design. Relational databases. Recovery, concurrency control. Normalization. ",
        "topics": ["Database Systems", "Design", "Concurrency Control"],
        "difficulty": 5,
        "favorite": true,
        "prereqs": ["251"],
        "typicalYear": "senior",
        "sections": ["lecture-discussion"],
        "image-url": "/../../assets/flowcharts/general.png",
        "course-type": "technical-elective"
    },
    {
        "name": "Big Data Mining",
        "id": "483",
        "credit_hours": "3",
        "description": "Data mining for very large datasets from a foundational and practical standpoint including similarity search, data-stream processing, advanced technology for search engines, recommendation systems, and graph analytics. ",
        "topics": ["Data Mining", "Database", "Analysis"],
        "difficulty": 5,
        "favorite": true,
        "prereqs": ["251"],
        "typicalYear": "senior",
        "sections": ["lecture-discussion"],
        "image-url": "/../../assets/flowcharts/general.png",
        "course-type": "technical-elective"
    },
    {
        "name": "Secure Web Application Development",
        "id": "484",
        "credit_hours": "3",
        "description": "Web applications integrate concepts from software engineering, systems programming, and computer security. Teaches security through web development, enabling students to design, deploy, scale, attack, and defend modern web applications. ",
        "topics": ["Web Dev", "React.JS", "Javascript", "Frameworks"],
        "difficulty": 3,
        "favorite": true,
        "prereqs": ["341"],
        "typicalYear": "senior",
        "sections": ["lecture-discussion"],
        "image-url": "/../../assets/flowcharts/general.png",
        "course-type": "technical-elective"
    },
    {
        "name": "Networked Operating Systems Programming",
        "id": "485",
        "credit_hours": "4",
        "description": "Concepts, design, and programming of multi-process and distributed systems; inter-process communications; fault tolerance; distributed programming semantics. Programming assignments and project required. ",
        "topics": ["Operating Systems", "Networking", "Design"],
        "difficulty": 5,
        "favorite": true,
        "prereqs": ["385"],
        "typicalYear": "senior",
        "sections": ["lecture-discussion"],
        "image-url": "/../../assets/flowcharts/general.png",
        "course-type": "technical-elective"
    },
    {
        "name": "Building Secure Computer Systems",
        "id": "487",
        "credit_hours": "3",
        "description": "Building and programming secure systems; protecting systems from threats and reduction of vulnerabilities; Includes application, host and network security. ",
        "topics": ["Computer Systems", "Security", "Network Security"],
        "difficulty": 5,
        "favorite": true,
        "prereqs": ["385"],
        "typicalYear": "senior",
        "sections": ["lecture-discussion"],
        "image-url": "/../../assets/flowcharts/cs487.png",
        "course-type": "technical-elective"
    },
    {
        "name": "Introduction to Cryptography",
        "id": "488",
        "credit_hours": "3",
        "description": "Foundational concepts: encryption schemes, hash functions, message authentication codes, digital signatures. Practical systems: stream and block ciphers, SHA. Advanced topics: secure computation, zero-knowledge proofs, blockchain. ",
        "topics": ["Cryptography", "Proofs", "Encryption"],
        "difficulty": 5,
        "favorite": true,
        "typicalYear": "senior",
        "sections": ["lecture-discussion"],
        "image-url": "/../../assets/flowcharts/general.png",
        "course-type": "technical-elective"
    },
    {
        "name": "Human Augmentics",
        "id": "489",
        "credit_hours": "3",
        "description": "Study of technologies for augmentation of human capabilities; human limitations; implants and wearable technologies; implants; brain-computer interfaces; exoskeletons; sensors and networks. Includes project work. ",
        "topics": ["Wearable Tech", "Analysis", "Hardware", "Network"],
        "difficulty": 5,
        "favorite": true,
        "prereqs": ["251"],
        "typicalYear": "senior",
        "sections": ["lecture-discussion"],
        "image-url": "/../../assets/flowcharts/general.png",
        "course-type": "technical-elective"
    },
    {
        "name": "Seminar",
        "id": "491",
        "credit_hours": "1-4",
        "description": "Topics of mutual interest to a faculty member and a group of students. Offered as announced by department bulletin or the Timetable. ",
        "topics": ["Seminar", "Multidisciplinary"],
        "difficulty": 2,
        "favorite": true,
        "prereqs": [],
        "typicalYear": "senior",
        "sections": ["discussion"],
        "image-url": "/../../assets/flowcharts/general.png",
        "course-type": "technical-elective"
    },
    {
        "name": "Special Topics in Computer Science",
        "id": "494",
        "credit_hours": "1-4",
        "description": "Multidisciplinary computer science topics for undergrad seniors and graduate student that vary from term to term depending on current student and instructor interests. ",
        "topics": ["Multidisciplinary"],
        "difficulty": 5,
        "favorite": true,
        "prereqs": [],
        "typicalYear": "senior",
        "sections": ["VARIES"],
        "image-url": "/../../assets/flowcharts/general.png",
        "course-type": "technical-elective"
    },
    {
        "name": "Professional Development Seminar",
        "id": "499",
        "credit_hours": "0",
        "description": "Graduating seniors will be provided with information regarding future career paths and will provide information regarding the program to be used for assessment purposes. Students take the CS Major Field Exam as part of this course. ",
        "topics": ["Seminar", "Multidisciplinary"],
        "difficulty": 5,
        "favorite": true,
        "prereqs": [],
        "typicalYear": "senior",
        "sections": ["discussion"],
        "image-url": "/../../assets/flowcharts/cs499.png",
        "course-type": "engineering-requirement"
    }
]